{"stats":{"minecraft:custom":{"minecraft:interact_with_furnace":14,"minecraft:mob_kills":2,"minecraft:interact_with_crafting_table":23,"minecraft:open_barrel":25,"minecraft:interact_with_stonecutter":2,"minecraft:leave_game":1,"minecraft:time_since_death":128849,"minecraft:sleep_in_bed":2,"minecraft:climb_one_cm":4036,"minecraft:time_since_rest":11054,"minecraft:sprint_one_cm":11161,"minecraft:damage_taken":301,"minecraft:walk_one_cm":404546,"minecraft:damage_dealt":579,"minecraft:swim_one_cm":4045,"minecraft:fly_one_cm":1378,"minecraft:open_chest":14,"minecraft:crouch_one_cm":2496,"minecraft:play_time":128849,"minecraft:sneak_time":1399,"minecraft:walk_under_water_one_cm":11463,"minecraft:jump":446,"minecraft:walk_on_water_one_cm":23758,"minecraft:total_world_time":128849,"minecraft:fall_one_cm":747},"minecraft:broken":{"minecraft:stone_pickaxe":7,"minecraft:wooden_axe":1},"minecraft:killed":{"minecraft:skeleton":1,"minecraft:zombie":1},"minecraft:mined":{"minecraft:oak_sapling":1,"minecraft:white_bed":1,"minecraft:torch":9,"minecraft:granite":67,"minecraft:cobblestone":7,"minecraft:copper_ore":7,"minecraft:diorite":9,"minecraft:wall_torch":19,"minecraft:oak_trapdoor":2,"minecraft:iron_ore":63,"minecraft:andesite":80,"minecraft:grass":57,"minecraft:oak_log":44,"minecraft:coal_ore":75,"minecraft:gravel":30,"minecraft:dripstone_block":2,"minecraft:dirt":137,"minecraft:stone":618,"minecraft:oak_leaves":57,"minecraft:deepslate":6},"minecraft:picked_up":{"minecraft:wooden_axe":1,"minecraft:cooked_beef":1,"minecraft:andesite":80,"minecraft:flint":3,"minecraft:oak_log":44,"minecraft:dirt":137,"minecraft:oak_trapdoor":2,"minecraft:raw_copper":17,"minecraft:cooked_mutton":3,"minecraft:bone":2,"minecraft:apple":1,"minecraft:wheat_seeds":6,"minecraft:cobbled_deepslate":6,"minecraft:iron_ingot":5,"minecraft:birch_sapling":1,"minecraft:stick":15,"minecraft:raw_iron":62,"minecraft:torch":35,"minecraft:spyglass":1,"minecraft:gravel":27,"minecraft:sand":5,"minecraft:diorite":12,"minecraft:white_bed":2,"minecraft:granite":67,"minecraft:oak_sapling":19,"minecraft:coal":70,"minecraft:cobblestone":542},"minecraft:used":{"minecraft:wheat_seeds":6,"minecraft:oak_trapdoor":3,"minecraft:cooked_mutton":3,"minecraft:water_bucket":24,"minecraft:diorite":6,"minecraft:cobblestone_stairs":12,"minecraft:stone_pickaxe":949,"minecraft:oak_planks":1,"minecraft:ladder":2,"minecraft:stone_hoe":66,"minecraft:stonecutter":1,"minecraft:torch":81,"minecraft:dirt":133,"minecraft:spyglass":2,"minecraft:crafting_table":1,"minecraft:campfire":1,"minecraft:white_bed":2,"minecraft:wooden_axe":6,"minecraft:birch_sapling":1,"minecraft:barrel":3,"minecraft:stone_axe":65,"minecraft:cobblestone":27,"minecraft:oak_sapling":11,"minecraft:furnace":1,"minecraft:beetroot_seeds":2,"minecraft:andesite":28,"minecraft:bucket":25,"minecraft:cooked_beef":1},"minecraft:crafted":{"minecraft:oak_planks":52,"minecraft:oak_slab":6,"minecraft:barrel":3,"minecraft:crafting_table":1,"minecraft:iron_helmet":1,"minecraft:furnace":1,"minecraft:copper_ingot":16,"minecraft:stone":8,"minecraft:bucket":2,"minecraft:campfire":1,"minecraft:stone_axe":3,"minecraft:air":0,"minecraft:oak_trapdoor":2,"minecraft:iron_boots":1,"minecraft:iron_chestplate":1,"minecraft:iron_axe":1,"minecraft:ladder":3,"minecraft:stick":48,"minecraft:iron_ingot":56,"minecraft:iron_pickaxe":1,"minecraft:stone_pickaxe":9,"minecraft:iron_leggings":1,"minecraft:stonecutter":1,"minecraft:stone_hoe":1,"minecraft:torch":52}},"DataVersion":2724}